penguins/__init__.py
penguins/_version.py
penguins/dataset.py
penguins/exportdeco.py
penguins/pgplot.py
penguins/plotutils.py
penguins/type_aliases.py
penguins-0.5.2.dist-info/LICENSE.txt
penguins-0.5.2.dist-info/METADATA
penguins-0.5.2.dist-info/WHEEL
penguins-0.5.2.dist-info/top_level.txt
penguins-0.5.2.dist-info/RECORD
