Metadata-Version: 2.1
Name: penguins
Version: 0.5.2
Summary: Penguins: an ENjoyable Gateway to Unpacking and Illustrating NMR Spectra
Home-page: https://github.com/yongrenjie/penguins
Author: Jonathan Yong
Author-email: yongrenjie@gmail.com
Classifier: Programming Language :: Python :: 3
Classifier: License :: OSI Approved :: MIT License
Classifier: Operating System :: OS Independent
Requires-Python: >=3.7
License-File: LICENSE.txt
Requires-Dist: numpy>=1.17.0
Requires-Dist: matplotlib
Requires-Dist: seaborn
